folder_duration/__init__.py
folder_duration/get_folder_duration.py
folder_duraton-0.1.dist-info/LICENSE
folder_duraton-0.1.dist-info/METADATA
folder_duraton-0.1.dist-info/WHEEL
folder_duraton-0.1.dist-info/entry_points.txt
folder_duraton-0.1.dist-info/top_level.txt
folder_duraton-0.1.dist-info/RECORD
